stucco_auth/__init__.py
stucco_auth/interfaces.py
stucco_auth/models.py
stucco_auth/security.py
stucco_auth/tables.py
stucco_auth/tm.py
stucco_auth/util.py
stucco_auth/views.py
stucco_auth/evolve/__init__.py
stucco_auth/evolve/create.py
stucco_auth/static/fauxform.html
stucco_auth/static/stucco_auth.css
stucco_auth/static/css/blue.uni-form.css
stucco_auth/static/css/dark.uni-form.css
stucco_auth/static/css/default.uni-form.css
stucco_auth/static/css/ready.uni-form.css
stucco_auth/static/css/uni-form.css
stucco_auth/static/js/uni-form.jquery.js
stucco_auth/templates/base.jinja2
stucco_auth/templates/form.jinja2
stucco_auth/templates/login.jinja2
stucco_auth/templates/welcome.jinja2
stucco_auth/tests/__init__.py
stucco_auth/tests/test_evolution.py
stucco_auth/tests/test_init.py
stucco_auth/tests/test_models.py
stucco_auth/tests/test_tm.py
stucco_auth/tests/tests.py
stucco_auth-0.7.1.dist-info/LICENSE.txt
stucco_auth-0.7.1.dist-info/METADATA
stucco_auth-0.7.1.dist-info/WHEEL
stucco_auth-0.7.1.dist-info/entry_points.txt
stucco_auth-0.7.1.dist-info/top_level.txt
stucco_auth-0.7.1.dist-info/RECORD
