Metadata-Version: 2.1
Name: stucco-auth
Version: 0.7.1
Summary: stucco_auth
Home-page: http://bitbucket.org/dholth/stucco_auth
Author: Daniel Holth
Author-email: dholth@fastmail.fm
License: BSD
Keywords: web pyramid pylons
Platform: UNKNOWN
Classifier: License :: OSI Approved :: BSD License
Classifier: Programming Language :: Python
Classifier: Topic :: Internet :: WWW/HTTP
Classifier: Topic :: Internet :: WWW/HTTP :: WSGI :: Application
Requires-Dist: cryptacular
Requires-Dist: pyramid
Requires-Dist: pyramid-beaker
Requires-Dist: pyramid-jinja2
Requires-Dist: stucco-evolution
Requires-Dist: SQLAlchemy
